django_kdl_wagtail-0.10.2.dist-info/DESCRIPTION.rst
django_kdl_wagtail-0.10.2.dist-info/METADATA
django_kdl_wagtail-0.10.2.dist-info/RECORD
django_kdl_wagtail-0.10.2.dist-info/WHEEL
django_kdl_wagtail-0.10.2.dist-info/metadata.json
django_kdl_wagtail-0.10.2.dist-info/top_level.txt
kdl_wagtail/__init__.py
kdl_wagtail/core/__init__.py
kdl_wagtail/core/admin.py
kdl_wagtail/core/api.py
kdl_wagtail/core/apps.py
kdl_wagtail/core/blocks.py
kdl_wagtail/core/models.py
kdl_wagtail/core/tests.py
kdl_wagtail/core/urls.py
kdl_wagtail/core/utils.py
kdl_wagtail/core/views.py
kdl_wagtail/core/migrations/0001_initial.py
kdl_wagtail/core/migrations/0002_analyticssettings_footersettings_indexpage.py
kdl_wagtail/core/migrations/0003_delete_footertext.py
kdl_wagtail/core/migrations/0004_add_tableblock_on_streampage.py
kdl_wagtail/core/migrations/0005_add_gallery_block.py
kdl_wagtail/core/migrations/0006_alignmentchoiceblock.py
kdl_wagtail/core/migrations/0007_add_annotation_fields.py
kdl_wagtail/core/migrations/0008_form_fields_order.py
kdl_wagtail/core/migrations/0009_pullquoteblock.py
kdl_wagtail/core/migrations/0010_add_display_to_embedblock.py
kdl_wagtail/core/migrations/0010_searchpage.py
kdl_wagtail/core/migrations/0011_auto_20190319_1311.py
kdl_wagtail/core/migrations/0012_merge_20190319_1526.py
kdl_wagtail/core/migrations/0013_auto_20190404_1142.py
kdl_wagtail/core/migrations/0014_add_links_to_imageblock.py
kdl_wagtail/core/migrations/0015_auto_20190505_0046.py
kdl_wagtail/core/migrations/0016_auto_20190505_0202.py
kdl_wagtail/core/migrations/0017_add_show_in_menus.py
kdl_wagtail/core/migrations/0018_sitemappage.py
kdl_wagtail/core/migrations/0019_richtextblock.py
kdl_wagtail/core/migrations/0020_contactusfield_clean_name.py
kdl_wagtail/core/migrations/0021_remove_contactusfield_clean_name.py
kdl_wagtail/core/migrations/0022_contactusfield_clean_name.py
kdl_wagtail/core/migrations/0023_proxypage.py
kdl_wagtail/core/migrations/0024_auto_20211008_1759.py
kdl_wagtail/core/migrations/__init__.py
kdl_wagtail/core/templates/kdl_wagtail_core/base.html
kdl_wagtail/core/templates/kdl_wagtail_core/base_contact_us_page.html
kdl_wagtail/core/templates/kdl_wagtail_core/base_contact_us_page_landing.html
