Metadata-Version: 2.0
Name: django-kdl-wagtail
Version: 0.10.2
Summary: KDL Wagtail Base Models
Home-page: https://github.com/kingsdigitallab/django-kdl-wagtail
Author: King's Digital Lab
Author-email: kdl-info@kcl.ac.uk
License: MIT
Keywords: django-kdl-wagtail
Platform: UNKNOWN
Classifier: Development Status :: 3 - Alpha
Classifier: Framework :: Django :: 2.0
Classifier: Intended Audience :: Developers
Classifier: License :: OSI Approved :: MIT License
Classifier: Natural Language :: English
Classifier: Programming Language :: Python :: 3
Classifier: Programming Language :: Python :: 3.5
Classifier: Programming Language :: Python :: 3.6
Classifier: Programming Language :: Python :: 3.7
License-File: LICENSE
License-File: AUTHORS.rst
Requires-Dist: wagtail (>=2.3)
